prefect_soda_cloud/__init__.py
prefect_soda_cloud/_version.py
prefect_soda_cloud/auth_config.py
prefect_soda_cloud/exceptions.py
prefect_soda_cloud/soda_cloud_client.py
prefect_soda_cloud/tasks.py
prefect_soda_cloud-0.0.1.dist-info/LICENSE
prefect_soda_cloud-0.0.1.dist-info/METADATA
prefect_soda_cloud-0.0.1.dist-info/WHEEL
prefect_soda_cloud-0.0.1.dist-info/entry_points.txt
prefect_soda_cloud-0.0.1.dist-info/top_level.txt
prefect_soda_cloud-0.0.1.dist-info/RECORD
